dbmisvc_test/__init__.py
dbmisvc_test/authentication.py
dbmisvc_test/request_response.py
dbmisvc_test/responses.py
dbmisvc_test/settings.py
dbmisvc_test/user.py
dbmisvc_test-1.0.0.dist-info/METADATA
dbmisvc_test-1.0.0.dist-info/WHEEL
dbmisvc_test-1.0.0.dist-info/top_level.txt
dbmisvc_test-1.0.0.dist-info/RECORD
