Metadata-Version: 2.2
Name: dbmisvc-test
Version: 1.0.0
Classifier: Development Status :: 4 - Beta
Classifier: Intended Audience :: Developers
Classifier: Topic :: Software Development :: Build Tools
Classifier: Programming Language :: Python :: 3
Classifier: Programming Language :: Python :: 3.11
Classifier: Programming Language :: Python :: 3.12
Requires-Python: >=3.11
Requires-Dist: django
Requires-Dist: django-dbmi-client
Requires-Dist: pyjwt
Requires-Dist: requests
Requires-Dist: responses
Provides-Extra: dev
Requires-Dist: pre-commit; extra == "dev"
